LICENSE.txt
MANIFEST.in
README.md
dependencies.txt
setup.py
strategies/__init__.py
strategies/core.py
strategies/dispatch.py
strategies/examples.py
strategies/term.py
strategies/tools.py
strategies/traverse.py
strategies/tree.py
strategies.egg-info/PKG-INFO
strategies.egg-info/SOURCES.txt
strategies.egg-info/dependency_links.txt
strategies.egg-info/not-zip-safe
strategies.egg-info/requires.txt
strategies.egg-info/top_level.txt
strategies/branch/__init__.py
strategies/branch/core.py