Metadata-Version: 1.0
Name: strategies
Version: 0.2.3
Summary: Strategic Programming in python
Home-page: http://github.com/logpy/strategies
Author: Matthew Rocklin
Author-email: mrocklin@gmail.com
License: BSD
Platform: UNKNOWN
